setup.py
distripack/Binomialdistribution.py
distripack/Gaussiandistribution.py
distripack/Generaldistribution.py
distripack/__init__.py
distripack.egg-info/PKG-INFO
distripack.egg-info/SOURCES.txt
distripack.egg-info/dependency_links.txt
distripack.egg-info/not-zip-safe
distripack.egg-info/top_level.txt