Metadata-Version: 1.0
Name: distripack
Version: 0.1
Summary: Gaussian distributions
Home-page: UNKNOWN
Author: himanshu_raw
Author-email: hr8077677@gmail.com
License: UNKNOWN
Platform: UNKNOWN
